{
    "languages": [
        {
            "option": "العربية",
            "symbol": ""
        },
        {
            "option": "español",
            "symbol": ""
        },
        {
            "option": "français",
            "symbol": ""
        },
        {
            "option": "Deutsch",
            "symbol": ""
        },
        {
            "option": "汉语",
            "symbol": ""
        },        {
            "option": "Italiano",
            "symbol": ""
        },        {
            "option": "Bahasa Indonesia",
            "symbol": ""
        },        {
            "option": "Português",
            "symbol": ""
        },
        {
            "option": "English",
            "symbol": ""
        },        {
            "option": "にほんご",
            "symbol": ""
        },        {
            "option": "한국어",
            "symbol": ""
        },        {
            "option": "русский",
            "symbol": ""
        },        {
            "option": "हिन्दी",
            "symbol": ""
        },
        {
            "option": "বাংলা",
            "symbol": ""
        },        {
            "option": "Türkçe",
            "symbol": ""
        },        {
            "option": "Nederlands",
            "symbol": ""
        },        {
            "option": "Melayu",
            "symbol": ""
        }
    ],
    "currencies": [
        {
            "option": "SAR | Saudi Arabia Riyal",
            "symbol": ""
        },
        {
            "option": "USD | United States Dollar",
            "symbol": ""
        },
        {
            "option": "TRY | Turkey Lira",
            "symbol": ""
        },
        {
            "option": "GBP | United Kingdom Pound",
            "symbol": ""
        },
        {
            "option": "RUB | Russia Ruble",
            "symbol": ""
        },
        {
            "option": "KRW | Korea (South) Won",
            "symbol": ""
        },
        {
            "option": "MYR | Malaysia Ringgit",
            "symbol": ""
        },
        {
            "option": "JPY | Japan Yen",
            "symbol": ""
        }
    ]
    
}